Topsis_HARMANJOT_102017043/Topsis_HARMANJOT_102017043.py
Topsis_HARMANJOT_102017043/__init__.py
packageharman/__init__.py
packageharman/topsis.py
Topsis_HARMANJOT_102017043-0.3.dist-info/License.txt.txt
Topsis_HARMANJOT_102017043-0.3.dist-info/METADATA
Topsis_HARMANJOT_102017043-0.3.dist-info/WHEEL
Topsis_HARMANJOT_102017043-0.3.dist-info/top_level.txt
Topsis_HARMANJOT_102017043-0.3.dist-info/RECORD
